apibench/__init__.py
apibench/apiclient.py
apibench-0.0.1.dist-info/METADATA
apibench-0.0.1.dist-info/WHEEL
apibench-0.0.1.dist-info/top_level.txt
apibench-0.0.1.dist-info/RECORD
