Metadata-Version: 2.1
Name: apibench
Version: 0.0.1
Summary: A reusable API library using httpx
Home-page: https://github.com/zeent/apibench
Author: Joan Camps Morey
Author-email: joan.camps@zeent.com
Classifier: Programming Language :: Python :: 3
Classifier: License :: OSI Approved :: MIT License
Classifier: Operating System :: OS Independent
Requires-Python: >=3.6
Requires-Dist: httpx
